siri_transit_api_client/__init__.py
siri_transit_api_client/exceptions.py
siri_transit_api_client/siri_client.py
siri_transit_api_client-0.2.1.dist-info/licenses/AUTHORS.rst
siri_transit_api_client-0.2.1.dist-info/licenses/LICENSE
siri_transit_api_client-0.2.1.dist-info/METADATA
siri_transit_api_client-0.2.1.dist-info/WHEEL
siri_transit_api_client-0.2.1.dist-info/top_level.txt
siri_transit_api_client-0.2.1.dist-info/RECORD
