Metadata-Version: 2.4
Name: siri-transit-api-client
Version: 0.2.1
Summary: API client to query transit data using SIRI (Service Interface for Real Time Information) framework. Verifierd to work on San Francisco Bay Area 511.org API
Author-email: Robert Hennessy <robertghennessy@gmail.com>
License: GNU GENERAL PUBLIC LICENSE
Project-URL: homepage, https://github.com/robertghennessy/siri_transit_api_client
Project-URL: documentation, https://github.com/robertghennessy/siri_transit_api_client
Project-URL: repository, https://github.com/robertghennessy/siri_transit_api_client
Keywords: 511.org,Transit,Open 511 APIs,Standard Interface for Real-time Information,SIRI
Classifier: Development Status :: 4 - Beta
Classifier: Intended Audience :: Developers
Classifier: Intended Audience :: Science/Research
Classifier: License :: OSI Approved :: GNU General Public License v3 (GPLv3)
Classifier: Natural Language :: English
Classifier: Operating System :: OS Independent
Classifier: Programming Language :: Python :: 3
Classifier: Programming Language :: Python :: 3 :: Only
Classifier: Programming Language :: Python :: 3.11
Classifier: Topic :: Scientific/Engineering
Requires-Python: >=3.11
License-File: LICENSE
License-File: AUTHORS.rst
Requires-Dist: requests>=2.27.1
Requires-Dist: responses>=0.20.0
Provides-Extra: test
Requires-Dist: pytest>=6.2.4; extra == "test"
Dynamic: license-file
